HISTORY.txt
README.txt
setup.cfg
setup.py
jyu/__init__.py
jyu.formwidget.object.egg-info/PKG-INFO
jyu.formwidget.object.egg-info/SOURCES.txt
jyu.formwidget.object.egg-info/dependency_links.txt
jyu.formwidget.object.egg-info/entry_points.txt
jyu.formwidget.object.egg-info/namespace_packages.txt
jyu.formwidget.object.egg-info/not-zip-safe
jyu.formwidget.object.egg-info/requires.txt
jyu.formwidget.object.egg-info/top_level.txt
jyu/formwidget/__init__.py
jyu/formwidget/object/__init__.py
jyu/formwidget/object/autoform.py
jyu/formwidget/object/configure.zcml
jyu/formwidget/object/converter.py
jyu/formwidget/object/datamanager.py
jyu/formwidget/object/factory.py
jyu/formwidget/object/object_display.pt
jyu/formwidget/object/object_input.pt
jyu/formwidget/object/overrides.zcml
jyu/formwidget/object/traversal.py
jyu/formwidget/object/validation.py