Metadata-Version: 1.0
Name: jyu.formwidget.object
Version: 1.0b6
Summary: Introduces experimental schema.Object support for plone.autoform and plone.app.z3cform.
Home-page: http://pypi.python.org/pypi/jyu.formwidget.object
Author: Asko Soukka
Author-email: asko.soukka@iki.fi
License: GPL
Platform: UNKNOWN
Classifier: Programming Language :: Python
Classifier: Topic :: Software Development :: Libraries :: Python Modules
